snowexsql/__init__.py
snowexsql/_version.py
snowexsql/api.py
snowexsql/conversions.py
snowexsql/db.py
snowexsql/functions.py
snowexsql/utilities.py
snowexsql/tables/__init__.py
snowexsql/tables/base.py
snowexsql/tables/campaign.py
snowexsql/tables/campaign_observation.py
snowexsql/tables/doi.py
snowexsql/tables/image_data.py
snowexsql/tables/image_observation.py
snowexsql/tables/instrument.py
snowexsql/tables/layer_data.py
snowexsql/tables/measurement_type.py
snowexsql/tables/observers.py
snowexsql/tables/point_data.py
snowexsql/tables/point_observation.py
snowexsql/tables/single_location.py
snowexsql/tables/site.py
snowexsql-1.0.0.dist-info/METADATA
snowexsql-1.0.0.dist-info/WHEEL
snowexsql-1.0.0.dist-info/licenses/LICENSE
snowexsql-1.0.0.dist-info/RECORD
