Metadata-Version: 2.4
Name: snowexsql
Version: 1.0.0
Summary: SQL Database software for SnowEx data
Project-URL: Homepage, https://github.com/SnowEx/snowexsql
Project-URL: Documentation, https://snowexsql.readthedocs.io
Project-URL: Repository, https://github.com/SnowEx/snowexsql.git
Project-URL: Issues, https://github.com/SnowEx/snowexsql/issues
License: GNU
License-File: LICENSE
Keywords: database,snow,snowex,sql
Classifier: Development Status :: 2 - Pre-Alpha
Classifier: Intended Audience :: Developers
Classifier: Natural Language :: English
Classifier: Programming Language :: Python :: 3.8
Classifier: Programming Language :: Python :: 3.9
Classifier: Programming Language :: Python :: 3.10
Requires-Python: >=3.8
Requires-Dist: geoalchemy2<1.0,>=0.6
Requires-Dist: geopandas<2.0,>=0.7
Requires-Dist: psycopg2-binary<2.10.0,>=2.9.0
Requires-Dist: rasterio>=1.1.5
Requires-Dist: sqlalchemy>=2.0.0
Requires-Dist: utm<1.0,>=0.5.0
Provides-Extra: all
Requires-Dist: factory-boy<4; extra == 'all'
Requires-Dist: ipython<9.0,>7.0; extra == 'all'
Requires-Dist: jupyter-book<1.1,>=1.0.2; extra == 'all'
Requires-Dist: nbconvert<6.5.0,>=6.4.3; extra == 'all'
Requires-Dist: nbsphinx==0.9.4; extra == 'all'
Requires-Dist: pandoc==1.0.2; extra == 'all'
Requires-Dist: plotly==5.22.0; extra == 'all'
Requires-Dist: pytest-cov; extra == 'all'
Requires-Dist: pytest-factoryboy<3; extra == 'all'
Requires-Dist: pytest<8.4; extra == 'all'
Requires-Dist: pyyaml<6.1; extra == 'all'
Requires-Dist: sphinx-autobuild<=2024.5; extra == 'all'
Requires-Dist: sphinx-gallery==0.9.0; extra == 'all'
Requires-Dist: sphinx<7.4,>=7.1; extra == 'all'
Requires-Dist: sphinxcontrib-apidoc==0.3.0; extra == 'all'
Provides-Extra: dev
Requires-Dist: factory-boy<4; extra == 'dev'
Requires-Dist: pytest-cov; extra == 'dev'
Requires-Dist: pytest-factoryboy<3; extra == 'dev'
Requires-Dist: pytest<8.4; extra == 'dev'
Requires-Dist: sphinx-autobuild<=2024.5; extra == 'dev'
Provides-Extra: docs
Requires-Dist: ipython<9.0,>7.0; extra == 'docs'
Requires-Dist: jupyter-book<1.1,>=1.0.2; extra == 'docs'
Requires-Dist: nbconvert<6.5.0,>=6.4.3; extra == 'docs'
Requires-Dist: nbsphinx==0.9.4; extra == 'docs'
Requires-Dist: pandoc==1.0.2; extra == 'docs'
Requires-Dist: plotly==5.22.0; extra == 'docs'
Requires-Dist: pyyaml<6.1; extra == 'docs'
Requires-Dist: sphinx-gallery==0.9.0; extra == 'docs'
Requires-Dist: sphinx<7.4,>=7.1; extra == 'docs'
Requires-Dist: sphinxcontrib-apidoc==0.3.0; extra == 'docs'
